benc/__init__.py
benc/__main__.py
benc/benc.py
benc-2019.8.1.dist-info/METADATA
benc-2019.8.1.dist-info/WHEEL
benc-2019.8.1.dist-info/top_level.txt
benc-2019.8.1.dist-info/RECORD
